archae/__init__.py
archae/__main__.py
archae/cli.py
archae/py.typed
archae/util/__init__.py
archae/util/archiver/__init__.py
archae/util/archiver/base_archiver.py
archae/util/archiver/peazip.py
archae/util/archiver/seven_zip.py
archae/util/archiver/unar.py
archae/util/enum/__init__.py
archae/util/enum/byte_scale.py
archae-2026.1.0.dist-info/WHEEL
archae-2026.1.0.dist-info/entry_points.txt
archae-2026.1.0.dist-info/METADATA
archae-2026.1.0.dist-info/RECORD
