Metadata-Version: 2.3
Name: archae
Version: 2026.1.0
Summary: Archae explodes archives.
Keywords: 
Author: Shawn McNaughton
Author-email: Shawn McNaughton <shawngmc@gmail.com>
License: MIT License
Classifier: Development Status :: 2 - Pre-Alpha
Classifier: Environment :: Console
Classifier: Intended Audience :: Developers
Classifier: License :: OSI Approved :: MIT License
Classifier: Programming Language :: Python
Classifier: Programming Language :: Python :: 3
Classifier: Programming Language :: Python :: 3.11
Classifier: Programming Language :: Python :: 3.12
Classifier: Programming Language :: Python :: 3.13
Classifier: Programming Language :: Python :: 3.14
Classifier: Programming Language :: Python :: 3 :: Only
Classifier: Typing :: Typed
Requires-Dist: click
Requires-Dist: python-magic
Requires-Dist: rich-click
Requires-Python: ~=3.11
Project-URL: Documentation, https://archae.readthedocs.io/en/stable/
Project-URL: Changelog, https://archae.readthedocs.io/en/stable/changelog.html
Project-URL: Source Code, https://github.com/shawngmc/archae
Project-URL: Issue Tracker, https://github.com/shawngmc/archae/issues
